{"course_name":"ITAL 404","subject_code":"ITAL","course_number":"404","course_title":"Italian Literature of the Middle Ages","course_link":"/cs/courseschedule?pname=subjarea&tname=subj-course&dept=ITAL&course=404&sessyr=2020&sesscd=W","sections":{"101":{"status":" ","section":"ITAL 404 101","href":"/cs/courseschedule?pname=subjarea&tname=subj-section&dept=ITAL&course=404&section=101&sessyr=2020&sesscd=W","activity":"Web-Oriented Course","term":"1","interval":"","days":" Tue Thu","start":"14:00","end":"15:30","comments":"Italian literature of the Middle Ages in its intellectual, socio-political and cultural context. Dante and his contemporaries and/or immediate followers (may include Petrarch and Boccaccio). Full description: https://fhis.ubc.ca/course-description/ital404/- cross-listed with ITST 414-101, RMST 420C-101 and RMST 520-101","subject_code":"ITAL","course_number":"404","section_number":"101","building":" ","room":"","instructors":["BOCCASSINI, DANIELA"],"totalRemaining":"10","currentlyRegistered":"0","generalRemaining":"10","restrictedRemaining":"0"}},"credits":"Credits: 3","description":"Italian literature of the Middle Ages in its intellectual, socio-political and cultural context. Dante and his contemporaries and/or immediate followers (may include Petrarch and Boccaccio). Precludes credit for ITST 414."}
