{"course_name":"PHIL 388","subject_code":"PHIL","course_number":"388","course_title":"Buddhist, Brahmanical and Jain Philosophers in Interaction.","course_link":"/cs/courseschedule?pname=subjarea&tname=subj-course&dept=PHIL&course=388&sessyr=2020&sesscd=W","sections":{"001":{"status":" ","section":"PHIL 388 001","href":"/cs/courseschedule?pname=subjarea&tname=subj-section&dept=PHIL&course=388&section=001&sessyr=2020&sesscd=W","activity":"Lecture","term":"2","interval":"","days":" Mon Wed Fri","start":"10:00","end":"11:00","comments":"","subject_code":"PHIL","course_number":"388","section_number":"001","building":"MacMillan","room":"160","instructors":["PRUEITT, CATHERINE"],"totalRemaining":"2","currentlyRegistered":"58","generalRemaining":"2","restrictedRemaining":"0"}},"credits":"Credits: 3","description":"Debates on issues of epistemology, language and ontology among the philosophical schools or systems of classical India Nagarjuna, Bhartrhari, Uma-svati, Sankara and others."}
