{"course_name":"FNH 340","subject_code":"FNH","course_number":"340","course_title":"Food Theory","course_link":"/cs/courseschedule?pname=subjarea&tname=subj-course&dept=FNH&course=340&sessyr=2020&sesscd=W","sections":{"001":{"status":"Full","section":"FNH 340 001","href":"/cs/courseschedule?pname=subjarea&tname=subj-section&dept=FNH&course=340&section=001&sessyr=2020&sesscd=W","activity":"Lecture","term":"2","interval":"","days":" Mon Fri","start":"9:30","end":"11:00","comments":"","subject_code":"FNH","course_number":"340","section_number":"001","building":"Food, Nutrition and Health","room":"50","instructors":["KASTEN, GERRY"],"totalRemaining":"0","currentlyRegistered":"43","generalRemaining":"0","restrictedRemaining":"0"}},"credits":"Credits: 3","description":"Principles of food preparation based on the physical and chemical properties of food."}
