{"course_name":"COMM 547B","subject_code":"COMM","course_number":"547B","course_title":"Major Essay/Industry Project - MAJOR ESSAY/PROJ","course_link":"/cs/courseschedule?pname=subjarea&tname=subj-course&dept=COMM&course=547B&sessyr=2020&sesscd=W","sections":{"610":{"status":"Blocked","section":"COMM 547B 610","href":"/cs/courseschedule?pname=subjarea&tname=subj-section&dept=COMM&course=547B&section=610&sessyr=2020&sesscd=W","activity":"Project","term":"1","interval":"","days":" ","start":" ","end":" ","comments":"","subject_code":"COMM","course_number":"547B","section_number":"610","building":"No Scheduled Meeting","room":"","instructors":["TBA"],"totalRemaining":"0","currentlyRegistered":"0","generalRemaining":"0","restrictedRemaining":"0"}},"credits":"Credits: 3","description":" "}
