{"course_name":"FRST 449D","subject_code":"FRST","course_number":"449D","course_title":"Directed Studies in Forestry - DIRECTED STUDIES","course_link":"/cs/courseschedule?pname=subjarea&tname=subj-course&dept=FRST&course=449D&sessyr=2020&sesscd=W","sections":{"104":{"status":"Blocked","section":"FRST 449D 104","href":"/cs/courseschedule?pname=subjarea&tname=subj-section&dept=FRST&course=449D&section=104&sessyr=2020&sesscd=W","activity":"Directed Studies","term":"1","interval":"","days":" ","start":" ","end":" ","comments":"","subject_code":"FRST","course_number":"449D","section_number":"104","building":"No Scheduled Meeting","room":"","instructors":["KOZAK, ROBERT ANTAL"],"totalRemaining":"0","currentlyRegistered":"0","generalRemaining":"0","restrictedRemaining":"0"},"204":{"status":"Blocked","section":"FRST 449D 204","href":"/cs/courseschedule?pname=subjarea&tname=subj-section&dept=FRST&course=449D&section=204&sessyr=2020&sesscd=W","activity":"Directed Studies","term":"2","interval":"","days":" ","start":" ","end":" ","comments":"","subject_code":"FRST","course_number":"449D","section_number":"204","building":"No Scheduled Meeting","room":"","instructors":["KOZAK, ROBERT ANTAL"],"totalRemaining":"0","currentlyRegistered":"0","generalRemaining":"0","restrictedRemaining":"0"}},"credits":"Credits: 4","description":"In special cases and with the approval of the instructor concerned, a student may carry on directed studies of specific problems in forestry."}
