{
  "course_name": "LAW 368D",
  "subject_code": "LAW",
  "course_number": "368D",
  "course_title": "Sexuality and Law - SEXUALITY & LAW",
  "course_link": "/cs/courseschedule?pname=subjarea&tname=subj-course&dept=LAW&course=368D&sessyr=2020&sesscd=W",
  "sections": [
    {
      "status": "Full",
      "section": "LAW 368D 001",
      "href": "/cs/courseschedule?pname=subjarea&tname=subj-section&dept=LAW&course=368D&section=001&sessyr=2020&sesscd=W",
      "activity": "Seminar",
      "term": "2",
      "interval": "",
      "days": [
        "THU"
      ],
      "start": "14:00",
      "end": "17:00",
      "comments": "",
      "subject_code": "LAW",
      "course_number": "368D",
      "section_number": "001",
      "building": " ",
      "room": "",
      "instructors": [
        "ALONI, EREZ"
      ],
      "totalRemaining": "0",
      "currentlyRegistered": "15",
      "generalRemaining": "0",
      "restrictedRemaining": "0"
    }
  ],
  "credits": 3,
  "description": "Legal issues relating to sexual activity, orientation and identification. Not offered each year, consult Faculty.",
  "terms": [
    "2"
  ],
  "activities": [
    "Seminar"
  ]
}
