{
  "course_name": "LAW 555D",
  "subject_code": "LAW",
  "course_number": "555D",
  "course_title": "Topics in Common Law Theory and Practice: Legal Theory and Practice - LEGAL THEORY",
  "course_link": "/cs/courseschedule?pname=subjarea&tname=subj-course&dept=LAW&course=555D&sessyr=2020&sesscd=W",
  "sections": [
    {
      "status": "Blocked",
      "section": "LAW 555D 003",
      "href": "/cs/courseschedule?pname=subjarea&tname=subj-section&dept=LAW&course=555D&section=003&sessyr=2020&sesscd=W",
      "activity": "Seminar",
      "term": "2",
      "interval": "",
      "days": [
        "TUE"
      ],
      "start": "14:00",
      "end": "17:00",
      "comments": "",
      "subject_code": "LAW",
      "course_number": "555D",
      "section_number": "003",
      "building": " ",
      "room": "",
      "instructors": [
        "ETXABE, JULEN"
      ],
      "totalRemaining": "0",
      "currentlyRegistered": "1",
      "generalRemaining": "0",
      "restrictedRemaining": "0"
    }
  ],
  "credits": "Credits: 4",
  "description": " ",
  "terms": [
    "2"
  ],
  "activities": [
    "Seminar"
  ]
}
