{
  "course_name": "DENT 769",
  "subject_code": "DENT",
  "course_number": "769",
  "course_title": "Foundation of Teaching and Learning for Dental Graduate Student Instructors (GSIs)",
  "course_link": "/cs/courseschedule?pname=subjarea&tname=subj-course&dept=DENT&course=769&sessyr=2020&sesscd=W",
  "sections": [
    {
      "status": "STT",
      "section": "DENT 769 001",
      "href": "/cs/courseschedule?pname=subjarea&tname=subj-section&dept=DENT&course=769&section=001&sessyr=2020&sesscd=W",
      "activity": "Lecture",
      "term": "1-2",
      "interval": "",
      "days": [
        ""
      ],
      "start": " ",
      "end": " ",
      "comments": "",
      "subject_code": "DENT",
      "course_number": "769",
      "section_number": "001",
      "building": "No Scheduled Meeting",
      "room": "",
      "instructors": [
        "VON BERGMANN, HSINGCHI"
      ],
      "totalRemaining": "",
      "currentlyRegistered": "",
      "generalRemaining": "",
      "restrictedRemaining": ""
    }
  ],
  "credits": "Credits: 3",
  "description": "Preparing dental graduate instructors to be effective teachers in dentistry. Spans from August of year 1 to August of year 2 for first year dental graduate students.",
  "terms": [
    "1-2"
  ],
  "activities": [
    "Lecture"
  ]
}
