{
  "course_name": "ENGL 100",
  "subject_code": "ENGL",
  "course_number": "100",
  "course_title": "Reading and Writing about Literature",
  "course_link": "/cs/courseschedule?pname=subjarea&tname=subj-course&dept=ENGL&course=100&sessyr=2020&sesscd=W",
  "sections": [
    {
      "status": "Full",
      "section": "ENGL 100 001",
      "href": "/cs/courseschedule?pname=subjarea&tname=subj-section&dept=ENGL&course=100&section=001&sessyr=2020&sesscd=W",
      "activity": "Web-Oriented Course",
      "term": "1",
      "interval": "",
      "days": [
        "MON",
        "WED",
        "FRI"
      ],
      "start": "09:00",
      "end": "10:00",
      "comments": "**ENGL 100 meets the 3.0 credit Faculty of Arts Writing requirement.  Students planning to seek a Major, Honours, or Minor degree in English are encouraged to take this course.  **Students require only one of WRDS 150, WRDS 350, ENGL 100, ARTS 001 (Arts One), or ASTU 100 or 101 (Coordinated Arts Program) to satisfy the Writing Component of the Writing and Research Requirement.**Open by permission to students outside Arts who are considering an ENGL minor and have strong ENGL 12 grades: first-year.english@ubc.caRESTRICTED TO STUDENTS IN ARTS, FINE ARTS, AND MUSIC.",
      "subject_code": "ENGL",
      "course_number": "100",
      "section_number": "001",
      "building": " ",
      "room": "",
      "instructors": [
        "ENDO, PAUL"
      ],
      "totalRemaining": "0",
      "currentlyRegistered": "30",
      "generalRemaining": "0",
      "restrictedRemaining": "0"
    },
    {
      "status": "Restricted",
      "section": "ENGL 100 002",
      "href": "/cs/courseschedule?pname=subjarea&tname=subj-section&dept=ENGL&course=100&section=002&sessyr=2020&sesscd=W",
      "activity": "Web-Oriented Course",
      "term": "1",
      "interval": "",
      "days": [
        "MON",
        "WED",
        "FRI"
      ],
      "start": "10:00",
      "end": "11:00",
      "comments": "**ENGL 100 meets the 3.0 credit Faculty of Arts Writing requirement.  Students planning to seek a Major, Honours, or Minor degree in English are encouraged to take this course.  **Students require only one of WRDS 150, WRDS 350, ENGL 100, ARTS 001 (Arts One), or ASTU 100 or 101 (Coordinated Arts Program) to satisfy the Writing Component of the Writing and Research Requirement.**Open by permission to students outside Arts who are considering an ENGL minor and have strong ENGL 12 grades: first-year.english@ubc.caRESTRICTED TO STUDENTS IN ARTS, FINE ARTS, AND MUSIC.",
      "subject_code": "ENGL",
      "course_number": "100",
      "section_number": "002",
      "building": " ",
      "room": "",
      "instructors": [
        "HART, ALEXANDER"
      ],
      "totalRemaining": "1",
      "currentlyRegistered": "29",
      "generalRemaining": "0",
      "restrictedRemaining": "1"
    },
    {
      "status": "Restricted",
      "section": "ENGL 100 003",
      "href": "/cs/courseschedule?pname=subjarea&tname=subj-section&dept=ENGL&course=100&section=003&sessyr=2020&sesscd=W",
      "activity": "Web-Oriented Course",
      "term": "1",
      "interval": "",
      "days": [
        "MON",
        "WED",
        "FRI"
      ],
      "start": "11:00",
      "end": "12:00",
      "comments": "**ENGL 100 meets the 3.0 credit Faculty of Arts Writing requirement.  Students planning to seek a Major, Honours, or Minor degree in English are encouraged to take this course.  **Students require only one of WRDS 150, WRDS 350, ENGL 100, ARTS 001 (Arts One), or ASTU 100 or 101 (Coordinated Arts Program) to satisfy the Writing Component of the Writing and Research Requirement.**Open by permission to students outside Arts who are considering an ENGL minor and have strong ENGL 12 grades: first-year.english@ubc.caRESTRICTED TO STUDENTS IN ARTS, FINE ARTS, AND MUSIC.",
      "subject_code": "ENGL",
      "course_number": "100",
      "section_number": "003",
      "building": " ",
      "room": "",
      "instructors": [
        "BAXTER, GISELE MARIE"
      ],
      "totalRemaining": "2",
      "currentlyRegistered": "28",
      "generalRemaining": "0",
      "restrictedRemaining": "2"
    },
    {
      "status": "Full",
      "section": "ENGL 100 004",
      "href": "/cs/courseschedule?pname=subjarea&tname=subj-section&dept=ENGL&course=100&section=004&sessyr=2020&sesscd=W",
      "activity": "Web-Oriented Course",
      "term": "1",
      "interval": "",
      "days": [
        "MON",
        "WED",
        "FRI"
      ],
      "start": "12:00",
      "end": "13:00",
      "comments": "**ENGL 100 meets the 3.0 credit Faculty of Arts Writing requirement.  Students planning to seek a Major, Honours, or Minor degree in English are encouraged to take this course.  **Students require only one of WRDS 150, WRDS 350, ENGL 100, ARTS 001 (Arts One), or ASTU 100 or 101 (Coordinated Arts Program) to satisfy the Writing Component of the Writing and Research Requirement.**Open by permission to students outside Arts who are considering an ENGL minor and have strong ENGL 12 grades: first-year.english@ubc.caRESTRICTED TO STUDENTS IN ARTS, FINE ARTS, AND MUSIC.",
      "subject_code": "ENGL",
      "course_number": "100",
      "section_number": "004",
      "building": " ",
      "room": "",
      "instructors": [
        "CULBERT, JOHN"
      ],
      "totalRemaining": "0",
      "currentlyRegistered": "30",
      "generalRemaining": "0",
      "restrictedRemaining": "0"
    },
    {
      "status": "Restricted",
      "section": "ENGL 100 005",
      "href": "/cs/courseschedule?pname=subjarea&tname=subj-section&dept=ENGL&course=100&section=005&sessyr=2020&sesscd=W",
      "activity": "Web-Oriented Course",
      "term": "1",
      "interval": "",
      "days": [
        "MON",
        "WED",
        "FRI"
      ],
      "start": "13:00",
      "end": "14:00",
      "comments": "**ENGL 100 meets the 3.0 credit Faculty of Arts Writing requirement.  Students planning to seek a Major, Honours, or Minor degree in English are encouraged to take this course.  **Students require only one of WRDS 150, WRDS 350, ENGL 100, ARTS 001 (Arts One), or ASTU 100 or 101 (Coordinated Arts Program) to satisfy the Writing Component of the Writing and Research Requirement.**Open by permission to students outside Arts who are considering an ENGL minor and have strong ENGL 12 grades: first-year.english@ubc.caRESTRICTED TO STUDENTS IN ARTS, FINE ARTS, AND MUSIC.",
      "subject_code": "ENGL",
      "course_number": "100",
      "section_number": "005",
      "building": " ",
      "room": "",
      "instructors": [
        "SCHOLES, JUDITH"
      ],
      "totalRemaining": "1",
      "currentlyRegistered": "29",
      "generalRemaining": "0",
      "restrictedRemaining": "1"
    },
    {
      "status": "Full",
      "section": "ENGL 100 006",
      "href": "/cs/courseschedule?pname=subjarea&tname=subj-section&dept=ENGL&course=100&section=006&sessyr=2020&sesscd=W",
      "activity": "Web-Oriented Course",
      "term": "1",
      "interval": "",
      "days": [
        "MON",
        "WED",
        "FRI"
      ],
      "start": "14:00",
      "end": "15:00",
      "comments": "**ENGL 100 meets the 3.0 credit Faculty of Arts Writing requirement.  Students planning to seek a Major, Honours, or Minor degree in English are encouraged to take this course.  **Students require only one of WRDS 150, WRDS 350, ENGL 100, ARTS 001 (Arts One), or ASTU 100 or 101 (Coordinated Arts Program) to satisfy the Writing Component of the Writing and Research Requirement.**Open by permission to students outside Arts who are considering an ENGL minor and have strong ENGL 12 grades: first-year.english@ubc.caRESTRICTED TO STUDENTS IN ARTS, FINE ARTS, AND MUSIC.",
      "subject_code": "ENGL",
      "course_number": "100",
      "section_number": "006",
      "building": " ",
      "room": "",
      "instructors": [
        "GOODING, RICHARD"
      ],
      "totalRemaining": "0",
      "currentlyRegistered": "31",
      "generalRemaining": "0",
      "restrictedRemaining": "0"
    },
    {
      "status": "Restricted",
      "section": "ENGL 100 007",
      "href": "/cs/courseschedule?pname=subjarea&tname=subj-section&dept=ENGL&course=100&section=007&sessyr=2020&sesscd=W",
      "activity": "Web-Oriented Course",
      "term": "1",
      "interval": "",
      "days": [
        "TUE",
        "THU"
      ],
      "start": "09:30",
      "end": "11:00",
      "comments": "**ENGL 100 meets the 3.0 credit Faculty of Arts Writing requirement.  Students planning to seek a Major, Honours, or Minor degree in English are encouraged to take this course.  **Students require only one of WRDS 150, WRDS 350, ENGL 100, ARTS 001 (Arts One), or ASTU 100 or 101 (Coordinated Arts Program) to satisfy the Writing Component of the Writing and Research Requirement.**Open by permission to students outside Arts who are considering an ENGL minor and have strong ENGL 12 grades: first-year.english@ubc.caRESTRICTED TO STUDENTS IN ARTS, FINE ARTS, AND MUSIC.",
      "subject_code": "ENGL",
      "course_number": "100",
      "section_number": "007",
      "building": " ",
      "room": "",
      "instructors": [
        "FOX, LORCAN FRANCIS"
      ],
      "totalRemaining": "1",
      "currentlyRegistered": "29",
      "generalRemaining": "0",
      "restrictedRemaining": "1"
    },
    {
      "status": "Restricted",
      "section": "ENGL 100 008",
      "href": "/cs/courseschedule?pname=subjarea&tname=subj-section&dept=ENGL&course=100&section=008&sessyr=2020&sesscd=W",
      "activity": "Web-Oriented Course",
      "term": "1",
      "interval": "",
      "days": [
        "TUE",
        "THU"
      ],
      "start": "11:00",
      "end": "12:30",
      "comments": "The instructor for this course is Alicia Fahey.**ENGL 100 meets the 3.0 credit Faculty of Arts Writing requirement.  Students planning to seek a Major, Honours, or Minor degree in English are encouraged to take this course.  **Students require only one of WRDS 150, WRDS 350, ENGL 100, ARTS 001 (Arts One), or ASTU 100 or 101 (Coordinated Arts Program) to satisfy the Writing Component of the Writing and Research Requirement.**Open by permission to students outside Arts who are considering an ENGL minor and have strong ENGL 12 grades: first-year.english@ubc.caRESTRICTED TO STUDENTS IN ARTS, FINE ARTS, AND MUSIC.",
      "subject_code": "ENGL",
      "course_number": "100",
      "section_number": "008",
      "building": " ",
      "room": "",
      "instructors": [
        "FAHEY, ALICIA"
      ],
      "totalRemaining": "2",
      "currentlyRegistered": "28",
      "generalRemaining": "0",
      "restrictedRemaining": "2"
    },
    {
      "status": "Full",
      "section": "ENGL 100 009",
      "href": "/cs/courseschedule?pname=subjarea&tname=subj-section&dept=ENGL&course=100&section=009&sessyr=2020&sesscd=W",
      "activity": "Web-Oriented Course",
      "term": "1",
      "interval": "",
      "days": [
        "TUE",
        "THU"
      ],
      "start": "12:30",
      "end": "14:00",
      "comments": "**ENGL 100 meets the 3.0 credit Faculty of Arts Writing requirement.  Students planning to seek a Major, Honours, or Minor degree in English are encouraged to take this course.  **Students require only one of WRDS 150, WRDS 350, ENGL 100, ARTS 001 (Arts One), or ASTU 100 or 101 (Coordinated Arts Program) to satisfy the Writing Component of the Writing and Research Requirement.**Open by permission to students outside Arts who are considering an ENGL minor and have strong ENGL 12 grades: first-year.english@ubc.caRESTRICTED TO STUDENTS IN ARTS, FINE ARTS, AND MUSIC.",
      "subject_code": "ENGL",
      "course_number": "100",
      "section_number": "009",
      "building": " ",
      "room": "",
      "instructors": [
        "GASTON, LISE"
      ],
      "totalRemaining": "0",
      "currentlyRegistered": "31",
      "generalRemaining": "0",
      "restrictedRemaining": "0"
    },
    {
      "status": "Full",
      "section": "ENGL 100 011",
      "href": "/cs/courseschedule?pname=subjarea&tname=subj-section&dept=ENGL&course=100&section=011&sessyr=2020&sesscd=W",
      "activity": "Web-Oriented Course",
      "term": "2",
      "interval": "",
      "days": [
        "MON",
        "WED",
        "FRI"
      ],
      "start": "10:00",
      "end": "11:00",
      "comments": "**ENGL 100 meets the 3.0 credit Faculty of Arts Writing requirement.  Students planning to seek a Major, Honours, or Minor degree in English are encouraged to take this course.  **Students require only one of WRDS 150, WRDS 350, ENGL 100, ARTS 001 (Arts One), or ASTU 100 or 101 (Coordinated Arts Program) to satisfy the Writing Component of the Writing and Research Requirement.**Open by permission to students outside Arts who are considering an ENGL minor and have strong ENGL 12 grades: first-year.english@ubc.caRESTRICTED TO STUDENTS IN ARTS, FINE ARTS, AND MUSIC.",
      "subject_code": "ENGL",
      "course_number": "100",
      "section_number": "011",
      "building": " ",
      "room": "",
      "instructors": [
        "FOX, LORCAN FRANCIS"
      ],
      "totalRemaining": "0",
      "currentlyRegistered": "33",
      "generalRemaining": "0",
      "restrictedRemaining": "0"
    },
    {
      "status": "Full",
      "section": "ENGL 100 012",
      "href": "/cs/courseschedule?pname=subjarea&tname=subj-section&dept=ENGL&course=100&section=012&sessyr=2020&sesscd=W",
      "activity": "Web-Oriented Course",
      "term": "2",
      "interval": "",
      "days": [
        "MON",
        "WED",
        "FRI"
      ],
      "start": "11:00",
      "end": "12:00",
      "comments": "**ENGL 100 meets the 3.0 credit Faculty of Arts Writing requirement.  Students planning to seek a Major, Honours, or Minor degree in English are encouraged to take this course.  **Students require only one of WRDS 150, WRDS 350, ENGL 100, ARTS 001 (Arts One), or ASTU 100 or 101 (Coordinated Arts Program) to satisfy the Writing Component of the Writing and Research Requirement.**Open by permission to students outside Arts who are considering an ENGL minor and have strong ENGL 12 grades: first-year.english@ubc.caRESTRICTED TO STUDENTS IN ARTS, FINE ARTS, AND MUSIC.",
      "subject_code": "ENGL",
      "course_number": "100",
      "section_number": "012",
      "building": " ",
      "room": "",
      "instructors": [
        "PARELES, MARISSA"
      ],
      "totalRemaining": "0",
      "currentlyRegistered": "33",
      "generalRemaining": "0",
      "restrictedRemaining": "0"
    },
    {
      "status": "Full",
      "section": "ENGL 100 013",
      "href": "/cs/courseschedule?pname=subjarea&tname=subj-section&dept=ENGL&course=100&section=013&sessyr=2020&sesscd=W",
      "activity": "Web-Oriented Course",
      "term": "2",
      "interval": "",
      "days": [
        "MON",
        "WED",
        "FRI"
      ],
      "start": "12:00",
      "end": "13:00",
      "comments": "**ENGL 100 meets the 3.0 credit Faculty of Arts Writing requirement.  Students planning to seek a Major, Honours, or Minor degree in English are encouraged to take this course.  **Students require only one of WRDS 150, WRDS 350, ENGL 100, ARTS 001 (Arts One), or ASTU 100 or 101 (Coordinated Arts Program) to satisfy the Writing Component of the Writing and Research Requirement.**Open by permission to students outside Arts who are considering an ENGL minor and have strong ENGL 12 grades: first-year.english@ubc.caRESTRICTED TO STUDENTS IN ARTS, FINE ARTS, AND MUSIC.",
      "subject_code": "ENGL",
      "course_number": "100",
      "section_number": "013",
      "building": " ",
      "room": "",
      "instructors": [
        "ENDO, PAUL"
      ],
      "totalRemaining": "0",
      "currentlyRegistered": "33",
      "generalRemaining": "0",
      "restrictedRemaining": "0"
    },
    {
      "status": "Full",
      "section": "ENGL 100 014",
      "href": "/cs/courseschedule?pname=subjarea&tname=subj-section&dept=ENGL&course=100&section=014&sessyr=2020&sesscd=W",
      "activity": "Web-Oriented Course",
      "term": "2",
      "interval": "",
      "days": [
        "MON",
        "WED",
        "FRI"
      ],
      "start": "13:00",
      "end": "14:00",
      "comments": "**ENGL 100 meets the 3.0 credit Faculty of Arts Writing requirement.  Students planning to seek a Major, Honours, or Minor degree in English are encouraged to take this course.  **Students require only one of WRDS 150, WRDS 350, ENGL 100, ARTS 001 (Arts One), or ASTU 100 or 101 (Coordinated Arts Program) to satisfy the Writing Component of the Writing and Research Requirement.**Open by permission to students outside Arts who are considering an ENGL minor and have strong ENGL 12 grades: first-year.english@ubc.caRESTRICTED TO STUDENTS IN ARTS, FINE ARTS, AND MUSIC.",
      "subject_code": "ENGL",
      "course_number": "100",
      "section_number": "014",
      "building": " ",
      "room": "",
      "instructors": [
        "HART, ALEXANDER"
      ],
      "totalRemaining": "0",
      "currentlyRegistered": "33",
      "generalRemaining": "0",
      "restrictedRemaining": "0"
    },
    {
      "status": "Full",
      "section": "ENGL 100 015",
      "href": "/cs/courseschedule?pname=subjarea&tname=subj-section&dept=ENGL&course=100&section=015&sessyr=2020&sesscd=W",
      "activity": "Web-Oriented Course",
      "term": "2",
      "interval": "",
      "days": [
        "MON",
        "WED",
        "FRI"
      ],
      "start": "14:00",
      "end": "15:00",
      "comments": "The instructor for this course is Alicia Fahey.**ENGL 100 meets the 3.0 credit Faculty of Arts Writing requirement.  Students planning to seek a Major, Honours, or Minor degree in English are encouraged to take this course.  **Students require only one of WRDS 150, WRDS 350, ENGL 100, ARTS 001 (Arts One), or ASTU 100 or 101 (Coordinated Arts Program) to satisfy the Writing Component of the Writing and Research Requirement.**Open by permission to students outside Arts who are considering an ENGL minor and have strong ENGL 12 grades: first-year.english@ubc.caRESTRICTED TO STUDENTS IN ARTS, FINE ARTS, AND MUSIC",
      "subject_code": "ENGL",
      "course_number": "100",
      "section_number": "015",
      "building": " ",
      "room": "",
      "instructors": [
        "FAHEY, ALICIA"
      ],
      "totalRemaining": "0",
      "currentlyRegistered": "33",
      "generalRemaining": "0",
      "restrictedRemaining": "0"
    },
    {
      "status": "Full",
      "section": "ENGL 100 016",
      "href": "/cs/courseschedule?pname=subjarea&tname=subj-section&dept=ENGL&course=100&section=016&sessyr=2020&sesscd=W",
      "activity": "Web-Oriented Course",
      "term": "2",
      "interval": "",
      "days": [
        "TUE",
        "THU"
      ],
      "start": "09:30",
      "end": "11:00",
      "comments": "**ENGL 100 meets the 3.0 credit Faculty of Arts Writing requirement.  Students planning to seek a Major, Honours, or Minor degree in English are encouraged to take this course.  **Students require only one of WRDS 150, WRDS 350, ENGL 100, ARTS 001 (Arts One), or ASTU 100 or 101 (Coordinated Arts Program) to satisfy the Writing Component of the Writing and Research Requirement.**Open by permission to students outside Arts who are considering an ENGL minor and have strong ENGL 12 grades: first-year.english@ubc.caRESTRICTED TO STUDENTS IN ARTS, FINE ARTS, AND MUSIC.",
      "subject_code": "ENGL",
      "course_number": "100",
      "section_number": "016",
      "building": " ",
      "room": "",
      "instructors": [
        "GRUBISIC, BRETT"
      ],
      "totalRemaining": "0",
      "currentlyRegistered": "33",
      "generalRemaining": "0",
      "restrictedRemaining": "0"
    },
    {
      "status": "Full",
      "section": "ENGL 100 017",
      "href": "/cs/courseschedule?pname=subjarea&tname=subj-section&dept=ENGL&course=100&section=017&sessyr=2020&sesscd=W",
      "activity": "Web-Oriented Course",
      "term": "2",
      "interval": "",
      "days": [
        "TUE",
        "THU"
      ],
      "start": "11:00",
      "end": "12:30",
      "comments": "**ENGL 100 meets the 3.0 credit Faculty of Arts Writing requirement.  Students planning to seek a Major, Honours, or Minor degree in English are encouraged to take this course.  **Students require only one of WRDS 150, WRDS 350, ENGL 100, ARTS 001 (Arts One), or ASTU 100 or 101 (Coordinated Arts Program) to satisfy the Writing Component of the Writing and Research Requirement.**Open by permission to students outside Arts who are considering an ENGL minor and have strong ENGL 12 grades: first-year.english@ubc.caRESTRICTED TO STUDENTS IN ARTS, FINE ARTS, AND MUSIC.",
      "subject_code": "ENGL",
      "course_number": "100",
      "section_number": "017",
      "building": " ",
      "room": "",
      "instructors": [
        "DREHER, GUDRUN"
      ],
      "totalRemaining": "0",
      "currentlyRegistered": "33",
      "generalRemaining": "0",
      "restrictedRemaining": "0"
    },
    {
      "status": "Full",
      "section": "ENGL 100 019",
      "href": "/cs/courseschedule?pname=subjarea&tname=subj-section&dept=ENGL&course=100&section=019&sessyr=2020&sesscd=W",
      "activity": "Web-Oriented Course",
      "term": "2",
      "interval": "",
      "days": [
        "TUE",
        "THU"
      ],
      "start": "14:00",
      "end": "15:30",
      "comments": "**ENGL 100 meets the 3.0 credit Faculty of Arts Writing requirement.  Students planning to seek a Major, Honours, or Minor degree in English are encouraged to take this course.  **Students require only one of WRDS 150, WRDS 350, ENGL 100, ARTS 001 (Arts One), or ASTU 100 or 101 (Coordinated Arts Program) to satisfy the Writing Component of the Writing and Research Requirement.**Open by permission to students outside Arts who are considering an ENGL minor and have strong ENGL 12 grades: first-year.english@ubc.caRESTRICTED TO STUDENTS IN ARTS, FINE ARTS, AND MUSIC.",
      "subject_code": "ENGL",
      "course_number": "100",
      "section_number": "019",
      "building": " ",
      "room": "",
      "instructors": [
        "BRIGGS, MARLENE"
      ],
      "totalRemaining": "0",
      "currentlyRegistered": "33",
      "generalRemaining": "0",
      "restrictedRemaining": "0"
    },
    {
      "status": "Unreleased",
      "section": "ENGL 100 01W",
      "href": "/cs/courseschedule?pname=subjarea&tname=subj-section&dept=ENGL&course=100&section=01W&sessyr=2020&sesscd=W",
      "activity": "Waiting List",
      "term": "1",
      "interval": "",
      "days": [
        "MON",
        "WED",
        "FRI"
      ],
      "start": "09:00",
      "end": "10:00",
      "comments": "-WAITING LIST.**ENGL 100 meets the 3.0 credit Faculty of Arts 'Writing' Requirement. **Students planning to seek a Major, Honours, or Minor degree in English are encouraged to take this course.**Students require only one of WRDS 150, WRDS 350, ENGL 100, ARTS 001 (Arts One), or ASTU 100 or 101 (Coordinated Arts Program) to satisfy the Writing Component of the Writing and Research Requirement.**Open by permission to students outside Arts who are considering an ENGL minor and have strong ENGL 12 grades: first-year.english@ubc.ca**RESTRICTED TO STUDENTS IN ARTS, FINE ARTS, AND MUSIC.",
      "subject_code": "ENGL",
      "course_number": "100",
      "section_number": "01W",
      "building": "To Be Announced",
      "room": "",
      "instructors": [
        "TBA"
      ],
      "totalRemaining": "0",
      "currentlyRegistered": "0",
      "generalRemaining": "0",
      "restrictedRemaining": "0"
    },
    {
      "status": "Unreleased",
      "section": "ENGL 100 02W",
      "href": "/cs/courseschedule?pname=subjarea&tname=subj-section&dept=ENGL&course=100&section=02W&sessyr=2020&sesscd=W",
      "activity": "Waiting List",
      "term": "1",
      "interval": "",
      "days": [
        "MON",
        "WED",
        "FRI"
      ],
      "start": "10:00",
      "end": "11:00",
      "comments": "-WAITING LIST.**ENGL 100 meets the 3.0 credit Faculty of Arts 'Writing' Requirement. **Students planning to seek a Major, Honours, or Minor degree in English are encouraged to take this course.**Students require only one of WRDS 150, WRDS 350, ENGL 100, ARTS 001 (Arts One), or ASTU 100 or 101 (Coordinated Arts Program) to satisfy the Writing Component of the Writing and Research Requirement.**Open by permission to students outside Arts who are considering an ENGL minor and have strong ENGL 12 grades: first-year.english@ubc.ca**RESTRICTED TO STUDENTS IN ARTS, FINE ARTS, AND MUSIC.",
      "subject_code": "ENGL",
      "course_number": "100",
      "section_number": "02W",
      "building": "To Be Announced",
      "room": "",
      "instructors": [
        "TBA"
      ],
      "totalRemaining": "0",
      "currentlyRegistered": "0",
      "generalRemaining": "0",
      "restrictedRemaining": "0"
    },
    {
      "status": "Unreleased",
      "section": "ENGL 100 03W",
      "href": "/cs/courseschedule?pname=subjarea&tname=subj-section&dept=ENGL&course=100&section=03W&sessyr=2020&sesscd=W",
      "activity": "Waiting List",
      "term": "1",
      "interval": "",
      "days": [
        "MON",
        "WED",
        "FRI"
      ],
      "start": "11:00",
      "end": "12:00",
      "comments": "-WAITING LIST.**ENGL 100 meets the 3.0 credit Faculty of Arts 'Writing' Requirement. **Students planning to seek a Major, Honours, or Minor degree in English are encouraged to take this course.**Students require only one of WRDS 150, WRDS 350, ENGL 100, ARTS 001 (Arts One), or ASTU 100 or 101 (Coordinated Arts Program) to satisfy the Writing Component of the Writing and Research Requirement.**Open by permission to students outside Arts who are considering an ENGL minor and have strong ENGL 12 grades: first-year.english@ubc.ca**RESTRICTED TO STUDENTS IN ARTS, FINE ARTS, AND MUSIC.",
      "subject_code": "ENGL",
      "course_number": "100",
      "section_number": "03W",
      "building": "To Be Announced",
      "room": "",
      "instructors": [
        "TBA"
      ],
      "totalRemaining": "0",
      "currentlyRegistered": "0",
      "generalRemaining": "0",
      "restrictedRemaining": "0"
    },
    {
      "status": "Unreleased",
      "section": "ENGL 100 04W",
      "href": "/cs/courseschedule?pname=subjarea&tname=subj-section&dept=ENGL&course=100&section=04W&sessyr=2020&sesscd=W",
      "activity": "Waiting List",
      "term": "1",
      "interval": "",
      "days": [
        "MON",
        "WED",
        "FRI"
      ],
      "start": "12:00",
      "end": "13:00",
      "comments": "-WAITING LIST.**ENGL 100 meets the 3.0 credit Faculty of Arts 'Writing' Requirement. **Students planning to seek a Major, Honours, or Minor degree in English are encouraged to take this course.**Students require only one of WRDS 150, WRDS 350, ENGL 100, ARTS 001 (Arts One), or ASTU 100 or 101 (Coordinated Arts Program) to satisfy the Writing Component of the Writing and Research Requirement.**Open by permission to students outside Arts who are considering an ENGL minor and have strong ENGL 12 grades: first-year.english@ubc.ca**RESTRICTED TO STUDENTS IN ARTS, FINE ARTS, AND MUSIC.",
      "subject_code": "ENGL",
      "course_number": "100",
      "section_number": "04W",
      "building": "To Be Announced",
      "room": "",
      "instructors": [
        "TBA"
      ],
      "totalRemaining": "0",
      "currentlyRegistered": "0",
      "generalRemaining": "0",
      "restrictedRemaining": "0"
    },
    {
      "status": "Full",
      "section": "ENGL 100 050",
      "href": "/cs/courseschedule?pname=subjarea&tname=subj-section&dept=ENGL&course=100&section=050&sessyr=2020&sesscd=W",
      "activity": "Web-Oriented Course",
      "term": "1",
      "interval": "",
      "days": [
        "TUE",
        "THU"
      ],
      "start": "19:00",
      "end": "20:30",
      "comments": "The instructor for this course is Thomas Vranken.**ENGL 100 meets the 3.0 credit Faculty of Arts Writing requirement.  Students planning to seek a Major, Honours, or Minor degree in English are encouraged to take this course.  **Students require only one of WRDS 150, WRDS 350, ENGL 100, ARTS 001 (Arts One), or ASTU 100 or 101 (Coordinated Arts Program) to satisfy the Writing Component of the Writing and Research Requirement.**Open by permission to students outside Arts who are considering an ENGL minor and have strong ENGL 12 grades: first-year.english@ubc.caRESTRICTED TO STUDENTS IN ARTS, FINE ARTS, AND MUSIC.INSTRUCTOR: THOMAS VRANKEN",
      "subject_code": "ENGL",
      "course_number": "100",
      "section_number": "050",
      "building": " ",
      "room": "",
      "instructors": [
        "VRANKEN, THOMAS"
      ],
      "totalRemaining": "0",
      "currentlyRegistered": "31",
      "generalRemaining": "0",
      "restrictedRemaining": "0"
    },
    {
      "status": "Unreleased",
      "section": "ENGL 100 05W",
      "href": "/cs/courseschedule?pname=subjarea&tname=subj-section&dept=ENGL&course=100&section=05W&sessyr=2020&sesscd=W",
      "activity": "Waiting List",
      "term": "1",
      "interval": "",
      "days": [
        "MON",
        "WED",
        "FRI"
      ],
      "start": "13:00",
      "end": "14:00",
      "comments": "-WAITING LIST.**ENGL 100 meets the 3.0 credit Faculty of Arts 'Writing' Requirement. **Students planning to seek a Major, Honours, or Minor degree in English are encouraged to take this course.**Students require only one of WRDS 150, WRDS 350, ENGL 100, ARTS 001 (Arts One), or ASTU 100 or 101 (Coordinated Arts Program) to satisfy the Writing Component of the Writing and Research Requirement.**Open by permission to students outside Arts who are considering an ENGL minor and have strong ENGL 12 grades: first-year.english@ubc.ca**RESTRICTED TO STUDENTS IN ARTS, FINE ARTS, AND MUSIC.",
      "subject_code": "ENGL",
      "course_number": "100",
      "section_number": "05W",
      "building": "To Be Announced",
      "room": "",
      "instructors": [
        "TBA"
      ],
      "totalRemaining": "0",
      "currentlyRegistered": "0",
      "generalRemaining": "0",
      "restrictedRemaining": "0"
    },
    {
      "status": "Unreleased",
      "section": "ENGL 100 06W",
      "href": "/cs/courseschedule?pname=subjarea&tname=subj-section&dept=ENGL&course=100&section=06W&sessyr=2020&sesscd=W",
      "activity": "Waiting List",
      "term": "1",
      "interval": "",
      "days": [
        "MON",
        "WED",
        "FRI"
      ],
      "start": "14:00",
      "end": "15:00",
      "comments": "-WAITING LIST.**ENGL 100 meets the 3.0 credit Faculty of Arts 'Writing' Requirement. **Students planning to seek a Major, Honours, or Minor degree in English are encouraged to take this course.**Students require only one of WRDS 150, WRDS 350, ENGL 100, ARTS 001 (Arts One), or ASTU 100 or 101 (Coordinated Arts Program) to satisfy the Writing Component of the Writing and Research Requirement.**Open by permission to students outside Arts who are considering an ENGL minor and have strong ENGL 12 grades: first-year.english@ubc.ca**RESTRICTED TO STUDENTS IN ARTS, FINE ARTS, AND MUSIC.",
      "subject_code": "ENGL",
      "course_number": "100",
      "section_number": "06W",
      "building": "To Be Announced",
      "room": "",
      "instructors": [
        "TBA"
      ],
      "totalRemaining": "0",
      "currentlyRegistered": "0",
      "generalRemaining": "0",
      "restrictedRemaining": "0"
    },
    {
      "status": "Unreleased",
      "section": "ENGL 100 07W",
      "href": "/cs/courseschedule?pname=subjarea&tname=subj-section&dept=ENGL&course=100&section=07W&sessyr=2020&sesscd=W",
      "activity": "Waiting List",
      "term": "1",
      "interval": "",
      "days": [
        "TUE",
        "THU"
      ],
      "start": "09:30",
      "end": "11:00",
      "comments": "-WAITING LIST.**ENGL 100 meets the 3.0 credit Faculty of Arts 'Writing' Requirement. **Students planning to seek a Major, Honours, or Minor degree in English are encouraged to take this course.**Students require only one of WRDS 150, WRDS 350, ENGL 100, ARTS 001 (Arts One), or ASTU 100 or 101 (Coordinated Arts Program) to satisfy the Writing Component of the Writing and Research Requirement.**Open by permission to students outside Arts who are considering an ENGL minor and have strong ENGL 12 grades: first-year.english@ubc.ca**RESTRICTED TO STUDENTS IN ARTS, FINE ARTS, AND MUSIC.",
      "subject_code": "ENGL",
      "course_number": "100",
      "section_number": "07W",
      "building": "To Be Announced",
      "room": "",
      "instructors": [
        "TBA"
      ],
      "totalRemaining": "0",
      "currentlyRegistered": "0",
      "generalRemaining": "0",
      "restrictedRemaining": "0"
    },
    {
      "status": "Unreleased",
      "section": "ENGL 100 08W",
      "href": "/cs/courseschedule?pname=subjarea&tname=subj-section&dept=ENGL&course=100&section=08W&sessyr=2020&sesscd=W",
      "activity": "Waiting List",
      "term": "1",
      "interval": "",
      "days": [
        "TUE",
        "THU"
      ],
      "start": "11:00",
      "end": "12:30",
      "comments": "-WAITING LIST.**ENGL 100 meets the 3.0 credit Faculty of Arts 'Writing' Requirement. **Students planning to seek a Major, Honours, or Minor degree in English are encouraged to take this course.**Students require only one of WRDS 150, WRDS 350, ENGL 100, ARTS 001 (Arts One), or ASTU 100 or 101 (Coordinated Arts Program) to satisfy the Writing Component of the Writing and Research Requirement.**Open by permission to students outside Arts who are considering an ENGL minor and have strong ENGL 12 grades: first-year.english@ubc.ca**RESTRICTED TO STUDENTS IN ARTS, FINE ARTS, AND MUSIC.",
      "subject_code": "ENGL",
      "course_number": "100",
      "section_number": "08W",
      "building": "To Be Announced",
      "room": "",
      "instructors": [
        "TBA"
      ],
      "totalRemaining": "0",
      "currentlyRegistered": "0",
      "generalRemaining": "0",
      "restrictedRemaining": "0"
    },
    {
      "status": "Unreleased",
      "section": "ENGL 100 09W",
      "href": "/cs/courseschedule?pname=subjarea&tname=subj-section&dept=ENGL&course=100&section=09W&sessyr=2020&sesscd=W",
      "activity": "Waiting List",
      "term": "1",
      "interval": "",
      "days": [
        "TUE",
        "THU"
      ],
      "start": "12:30",
      "end": "14:00",
      "comments": "-WAITING LIST.**ENGL 100 meets the 3.0 credit Faculty of Arts 'Writing' Requirement. **Students planning to seek a Major, Honours, or Minor degree in English are encouraged to take this course.**Students require only one of WRDS 150, WRDS 350, ENGL 100, ARTS 001 (Arts One), or ASTU 100 or 101 (Coordinated Arts Program) to satisfy the Writing Component of the Writing and Research Requirement.**Open by permission to students outside Arts who are considering an ENGL minor and have strong ENGL 12 grades: first-year.english@ubc.ca**RESTRICTED TO STUDENTS IN ARTS, FINE ARTS, AND MUSIC.",
      "subject_code": "ENGL",
      "course_number": "100",
      "section_number": "09W",
      "building": "To Be Announced",
      "room": "",
      "instructors": [
        "TBA"
      ],
      "totalRemaining": "0",
      "currentlyRegistered": "0",
      "generalRemaining": "0",
      "restrictedRemaining": "0"
    },
    {
      "status": "Full",
      "section": "ENGL 100 11W",
      "href": "/cs/courseschedule?pname=subjarea&tname=subj-section&dept=ENGL&course=100&section=11W&sessyr=2020&sesscd=W",
      "activity": "Waiting List",
      "term": "2",
      "interval": "",
      "days": [
        "MON",
        "WED",
        "FRI"
      ],
      "start": "10:00",
      "end": "11:00",
      "comments": "-WAITING LIST.**ENGL 100 meets the 3.0 credit Faculty of Arts 'Writing' Requirement. **Students planning to seek a Major, Honours, or Minor degree in English are encouraged to take this course.**Students require only one of WRDS 150, WRDS 350, ENGL 100, ARTS 001 (Arts One), or ASTU 100 or 101 (Coordinated Arts Program) to satisfy the Writing Component of the Writing and Research Requirement.**Open by permission to students outside Arts who are considering an ENGL minor and have strong ENGL 12 grades: first-year.english@ubc.ca**RESTRICTED TO STUDENTS IN ARTS, FINE ARTS, AND MUSIC.",
      "subject_code": "ENGL",
      "course_number": "100",
      "section_number": "11W",
      "building": " ",
      "room": "",
      "instructors": [
        "TBA"
      ],
      "totalRemaining": "0",
      "currentlyRegistered": "5",
      "generalRemaining": "0",
      "restrictedRemaining": "0"
    },
    {
      "status": "Full",
      "section": "ENGL 100 12W",
      "href": "/cs/courseschedule?pname=subjarea&tname=subj-section&dept=ENGL&course=100&section=12W&sessyr=2020&sesscd=W",
      "activity": "Waiting List",
      "term": "2",
      "interval": "",
      "days": [
        "MON",
        "WED",
        "FRI"
      ],
      "start": "11:00",
      "end": "12:00",
      "comments": "-WAITING LIST.**ENGL 100 meets the 3.0 credit Faculty of Arts 'Writing' Requirement. **Students planning to seek a Major, Honours, or Minor degree in English are encouraged to take this course.**Students require only one of WRDS 150, WRDS 350, ENGL 100, ARTS 001 (Arts One), or ASTU 100 or 101 (Coordinated Arts Program) to satisfy the Writing Component of the Writing and Research Requirement.**Open by permission to students outside Arts who are considering an ENGL minor and have strong ENGL 12 grades: first-year.english@ubc.ca**RESTRICTED TO STUDENTS IN ARTS, FINE ARTS, AND MUSIC.",
      "subject_code": "ENGL",
      "course_number": "100",
      "section_number": "12W",
      "building": " ",
      "room": "",
      "instructors": [
        "TBA"
      ],
      "totalRemaining": "0",
      "currentlyRegistered": "6",
      "generalRemaining": "0",
      "restrictedRemaining": "0"
    },
    {
      "status": "Full",
      "section": "ENGL 100 13W",
      "href": "/cs/courseschedule?pname=subjarea&tname=subj-section&dept=ENGL&course=100&section=13W&sessyr=2020&sesscd=W",
      "activity": "Waiting List",
      "term": "2",
      "interval": "",
      "days": [
        "MON",
        "WED",
        "FRI"
      ],
      "start": "12:00",
      "end": "13:00",
      "comments": "-WAITING LIST.**ENGL 100 meets the 3.0 credit Faculty of Arts 'Writing' Requirement. **Students planning to seek a Major, Honours, or Minor degree in English are encouraged to take this course.**Students require only one of WRDS 150, WRDS 350, ENGL 100, ARTS 001 (Arts One), or ASTU 100 or 101 (Coordinated Arts Program) to satisfy the Writing Component of the Writing and Research Requirement.**Open by permission to students outside Arts who are considering an ENGL minor and have strong ENGL 12 grades: first-year.english@ubc.ca**RESTRICTED TO STUDENTS IN ARTS, FINE ARTS, AND MUSIC.",
      "subject_code": "ENGL",
      "course_number": "100",
      "section_number": "13W",
      "building": " ",
      "room": "",
      "instructors": [
        "TBA"
      ],
      "totalRemaining": "0",
      "currentlyRegistered": "5",
      "generalRemaining": "0",
      "restrictedRemaining": "0"
    },
    {
      "status": "Full",
      "section": "ENGL 100 14W",
      "href": "/cs/courseschedule?pname=subjarea&tname=subj-section&dept=ENGL&course=100&section=14W&sessyr=2020&sesscd=W",
      "activity": "Waiting List",
      "term": "2",
      "interval": "",
      "days": [
        "MON",
        "WED",
        "FRI"
      ],
      "start": "13:00",
      "end": "14:00",
      "comments": "-WAITING LIST.**ENGL 100 meets the 3.0 credit Faculty of Arts 'Writing' Requirement. **Students planning to seek a Major, Honours, or Minor degree in English are encouraged to take this course.**Students require only one of WRDS 150, WRDS 350, ENGL 100, ARTS 001 (Arts One), or ASTU 100 or 101 (Coordinated Arts Program) to satisfy the Writing Component of the Writing and Research Requirement.**Open by permission to students outside Arts who are considering an ENGL minor and have strong ENGL 12 grades: first-year.english@ubc.ca**RESTRICTED TO STUDENTS IN ARTS, FINE ARTS, AND MUSIC.",
      "subject_code": "ENGL",
      "course_number": "100",
      "section_number": "14W",
      "building": " ",
      "room": "",
      "instructors": [
        "TBA"
      ],
      "totalRemaining": "0",
      "currentlyRegistered": "4",
      "generalRemaining": "0",
      "restrictedRemaining": "0"
    },
    {
      "status": "Full",
      "section": "ENGL 100 15W",
      "href": "/cs/courseschedule?pname=subjarea&tname=subj-section&dept=ENGL&course=100&section=15W&sessyr=2020&sesscd=W",
      "activity": "Waiting List",
      "term": "2",
      "interval": "",
      "days": [
        "MON",
        "WED",
        "FRI"
      ],
      "start": "14:00",
      "end": "15:00",
      "comments": "-WAITING LIST.**ENGL 100 meets the 3.0 credit Faculty of Arts 'Writing' Requirement. **Students planning to seek a Major, Honours, or Minor degree in English are encouraged to take this course.**Students require only one of WRDS 150, WRDS 350, ENGL 100, ARTS 001 (Arts One), or ASTU 100 or 101 (Coordinated Arts Program) to satisfy the Writing Component of the Writing and Research Requirement.**Open by permission to students outside Arts who are considering an ENGL minor and have strong ENGL 12 grades: first-year.english@ubc.ca**RESTRICTED TO STUDENTS IN ARTS, FINE ARTS, AND MUSIC.",
      "subject_code": "ENGL",
      "course_number": "100",
      "section_number": "15W",
      "building": " ",
      "room": "",
      "instructors": [
        "TBA"
      ],
      "totalRemaining": "0",
      "currentlyRegistered": "2",
      "generalRemaining": "0",
      "restrictedRemaining": "0"
    },
    {
      "status": "Full",
      "section": "ENGL 100 16W",
      "href": "/cs/courseschedule?pname=subjarea&tname=subj-section&dept=ENGL&course=100&section=16W&sessyr=2020&sesscd=W",
      "activity": "Waiting List",
      "term": "2",
      "interval": "",
      "days": [
        "TUE",
        "THU"
      ],
      "start": "09:30",
      "end": "11:00",
      "comments": "-WAITING LIST.**ENGL 100 meets the 3.0 credit Faculty of Arts 'Writing' Requirement. **Students planning to seek a Major, Honours, or Minor degree in English are encouraged to take this course.**Students require only one of WRDS 150, WRDS 350, ENGL 100, ARTS 001 (Arts One), or ASTU 100 or 101 (Coordinated Arts Program) to satisfy the Writing Component of the Writing and Research Requirement.**Open by permission to students outside Arts who are considering an ENGL minor and have strong ENGL 12 grades: first-year.english@ubc.ca**RESTRICTED TO STUDENTS IN ARTS, FINE ARTS, AND MUSIC.",
      "subject_code": "ENGL",
      "course_number": "100",
      "section_number": "16W",
      "building": " ",
      "room": "",
      "instructors": [
        "TBA"
      ],
      "totalRemaining": "0",
      "currentlyRegistered": "4",
      "generalRemaining": "0",
      "restrictedRemaining": "0"
    },
    {
      "status": "Full",
      "section": "ENGL 100 17W",
      "href": "/cs/courseschedule?pname=subjarea&tname=subj-section&dept=ENGL&course=100&section=17W&sessyr=2020&sesscd=W",
      "activity": "Waiting List",
      "term": "2",
      "interval": "",
      "days": [
        "TUE",
        "THU"
      ],
      "start": "11:00",
      "end": "12:30",
      "comments": "-WAITING LIST.**ENGL 100 meets the 3.0 credit Faculty of Arts 'Writing' Requirement. **Students planning to seek a Major, Honours, or Minor degree in English are encouraged to take this course.**Students require only one of WRDS 150, WRDS 350, ENGL 100, ARTS 001 (Arts One), or ASTU 100 or 101 (Coordinated Arts Program) to satisfy the Writing Component of the Writing and Research Requirement.**Open by permission to students outside Arts who are considering an ENGL minor and have strong ENGL 12 grades: first-year.english@ubc.ca**RESTRICTED TO STUDENTS IN ARTS, FINE ARTS, AND MUSIC.",
      "subject_code": "ENGL",
      "course_number": "100",
      "section_number": "17W",
      "building": " ",
      "room": "",
      "instructors": [
        "TBA"
      ],
      "totalRemaining": "0",
      "currentlyRegistered": "5",
      "generalRemaining": "0",
      "restrictedRemaining": "0"
    },
    {
      "status": "Full",
      "section": "ENGL 100 19W",
      "href": "/cs/courseschedule?pname=subjarea&tname=subj-section&dept=ENGL&course=100&section=19W&sessyr=2020&sesscd=W",
      "activity": "Waiting List",
      "term": "2",
      "interval": "",
      "days": [
        "TUE",
        "THU"
      ],
      "start": "14:00",
      "end": "15:30",
      "comments": "-WAITING LIST.**ENGL 100 meets the 3.0 credit Faculty of Arts 'Writing' Requirement. **Students planning to seek a Major, Honours, or Minor degree in English are encouraged to take this course.**Students require only one of WRDS 150, WRDS 350, ENGL 100, ARTS 001 (Arts One), or ASTU 100 or 101 (Coordinated Arts Program) to satisfy the Writing Component of the Writing and Research Requirement.**Open by permission to students outside Arts who are considering an ENGL minor and have strong ENGL 12 grades: first-year.english@ubc.ca**RESTRICTED TO STUDENTS IN ARTS, FINE ARTS, AND MUSIC.",
      "subject_code": "ENGL",
      "course_number": "100",
      "section_number": "19W",
      "building": " ",
      "room": "",
      "instructors": [
        "TBA"
      ],
      "totalRemaining": "0",
      "currentlyRegistered": "5",
      "generalRemaining": "0",
      "restrictedRemaining": "0"
    },
    {
      "status": "Unreleased",
      "section": "ENGL 100 50W",
      "href": "/cs/courseschedule?pname=subjarea&tname=subj-section&dept=ENGL&course=100&section=50W&sessyr=2020&sesscd=W",
      "activity": "Waiting List",
      "term": "1",
      "interval": "",
      "days": [
        "TUE",
        "THU"
      ],
      "start": "19:00",
      "end": "20:30",
      "comments": "-WAITING LIST.**ENGL 100 meets the 3.0 credit Faculty of Arts 'Writing' Requirement. **Students planning to seek a Major, Honours, or Minor degree in English are encouraged to take this course.**Students require only one of WRDS 150, WRDS 350, ENGL 100, ARTS 001 (Arts One), or ASTU 100 or 101 (Coordinated Arts Program) to satisfy the Writing Component of the Writing and Research Requirement.**Open by permission to students outside Arts who are considering an ENGL minor and have strong ENGL 12 grades: first-year.english@ubc.ca**RESTRICTED TO STUDENTS IN ARTS, FINE ARTS, AND MUSIC.",
      "subject_code": "ENGL",
      "course_number": "100",
      "section_number": "50W",
      "building": " ",
      "room": "",
      "instructors": [
        "TBA"
      ],
      "totalRemaining": "0",
      "currentlyRegistered": "0",
      "generalRemaining": "0",
      "restrictedRemaining": "0"
    }
  ],
  "credits": "Credits: 3",
  "description": "A writing-intensive introduction to the disciplines of literary studies through the exploration of texts in their critical and theoretical contexts. Fulfils the first-year component of the Faculty of Arts Writing and Research Requirement. Open only to students in the Faculty of Arts. Recommended for students intending to become English majors. Essays are required.",
  "terms": [
    "1",
    "2"
  ],
  "activities": [
    "Web-Oriented Course",
    "Waiting List"
  ]
}
